vuln_checker/__init__.py
vuln_checker/cpes_list.txt
vuln_checker/excluded_cpes.txt
vuln_checker/main.py
vuln_checker/products.csv
vuln_checker/requirements.txt
vuln_checker/templates/template.html
vuln_checker-0.5.5.dist-info/licenses/LICENSE
vuln_checker-0.5.5.dist-info/METADATA
vuln_checker-0.5.5.dist-info/WHEEL
vuln_checker-0.5.5.dist-info/entry_points.txt
vuln_checker-0.5.5.dist-info/top_level.txt
vuln_checker-0.5.5.dist-info/RECORD
