Metadata-Version: 2.4
Name: vuln-checker
Version: 0.5.5
Summary: CLI tool to fetch CVEs using NVD Feeds
Author-email: skm248 <saikrishnameda248@outlook.com>
License-Expression: MIT
Keywords: cve,vulnerability,cli,security,nvd,cpe
Requires-Python: >=3.7
License-File: LICENSE
Requires-Dist: charset-normalizer==3.4.1
Requires-Dist: idna==3.10
Requires-Dist: jinja2==3.1.6
Requires-Dist: markupsafe==3.0.2
Requires-Dist: packaging==25.0
Requires-Dist: requests==2.32.3
Requires-Dist: urllib3==1.26.20
Requires-Dist: certifi==2025.1.31
Requires-Dist: tomli>=2.0.1; python_version < "3.11"
Requires-Dist: tqdm>=4.65.0
Requires-Dist: openpyxl>=3.1.5
Dynamic: license-file
